<?xml version="1.0" encoding="UTF-8"?>
<con:soapui-project id="3fb78446-3175-49c6-82d7-d4e8ecb8cd34" created="3.30.0" activeEnvironment="Default environment" name="PostDelete_key" resourceRoot="" updated="3.30.0 2022-03-16T13:04:41Z" xmlns:con="http://eviware.com/soapui/config">
  <con:settings/>
  <con:interface xsi:type="con:RestService" id="018ccb73-36f4-4ffb-a8f6-bea8e93c457c" wadlVersion="http://wadl.dev.java.net/2009/02" name="https://api.github.com" type="rest" xmlns:xsi="http://www.w3.org/2001/XMLSchema-instance">
    <con:settings/>
    <con:definitionCache type="TEXT" rootPart=""/>
    <con:endpoints>
      <con:endpoint>https://api.github.com</con:endpoint>
    </con:endpoints>
    <con:resource name="Keys" path="/user/keys" id="c2cbc472-9409-4aaf-b259-e671fd31fe51">
      <con:settings/>
      <con:parameters/>
      <con:resource name="{keyId}" path="{keyId}" id="58c626e1-41ec-471c-b9cf-fb0982878753">
        <con:settings/>
        <con:parameters>
          <con:parameter required="true">
            <con:name>keyId</con:name>
            <con:value>keyId</con:value>
            <con:style>TEMPLATE</con:style>
            <con:default>keyId</con:default>
          </con:parameter>
        </con:parameters>
        <con:method name="Method 1" id="f556c54c-18d4-4f26-b745-09f7f8a2a996" method="DELETE">
          <con:settings/>
          <con:parameters/>
          <con:representation type="RESPONSE">
            <con:mediaType xsi:nil="true"/>
            <con:status>204</con:status>
            <con:params/>
            <con:element>data</con:element>
          </con:representation>
          <con:representation type="REQUEST">
            <con:mediaType>application/json</con:mediaType>
            <con:params/>
          </con:representation>
          <con:representation type="FAULT">
            <con:mediaType>application/json; charset=utf-8</con:mediaType>
            <con:status>404</con:status>
            <con:params/>
            <con:element xmlns:ns="https://api.github.com/user/keys/66838536">ns:Fault</con:element>
          </con:representation>
          <con:request name="Request 1" id="b1b99dd8-2a5a-48f9-a151-d42a2249c4f4" mediaType="application/json" postQueryString="false">
            <con:settings/>
            <con:endpoint>https://api.github.com</con:endpoint>
            <con:request/>
            <con:credentials>
              <con:authType>No Authorization</con:authType>
            </con:credentials>
            <con:jmsConfig JMSDeliveryMode="PERSISTENT"/>
            <con:parameters/>
          </con:request>
        </con:method>
      </con:resource>
      <con:method name="Keys" id="61cfca74-5a55-4c99-86e4-4e1bec97e045" method="POST">
        <con:settings/>
        <con:parameters/>
        <con:representation type="REQUEST">
          <con:mediaType>application/json</con:mediaType>
          <con:params/>
        </con:representation>
        <con:representation type="RESPONSE">
          <con:mediaType>application/json; charset=utf-8</con:mediaType>
          <con:status>201</con:status>
          <con:params/>
          <con:element xmlns:keys="https://api.github.com/user/keys">keys:Response</con:element>
        </con:representation>
        <con:representation type="FAULT">
          <con:mediaType>application/json; charset=utf-8</con:mediaType>
          <con:status>422</con:status>
          <con:params/>
          <con:element xmlns:keys="https://api.github.com/user/keys">keys:Fault</con:element>
        </con:representation>
        <con:request name="Request 1" id="9dfeece6-8fea-4ab7-8d50-9684650c5a0d" mediaType="application/json" postQueryString="false">
          <con:settings/>
          <con:endpoint>https://api.github.com</con:endpoint>
          <con:request/>
          <con:credentials>
            <con:authType>No Authorization</con:authType>
          </con:credentials>
          <con:jmsConfig JMSDeliveryMode="PERSISTENT"/>
          <con:parameters/>
        </con:request>
      </con:method>
    </con:resource>
  </con:interface>
  <con:testSuite id="0190b894-eb6b-4147-83bd-452cae9373fe" name="https://api.github.com Test Suite">
    <con:settings/>
    <con:runType>SEQUENTIAL</con:runType>
    <con:testCase id="83ba0a7b-c504-4cbc-856d-6ab207fbc5f2" discardOkResults="false" failOnError="true" failTestCaseOnErrors="true" keepSession="false" name="https://api.github.com Test Case 1" searchProperties="true" timeout="0">
      <con:settings/>
      <con:testStep type="restrequest" name="POST Request 1" id="cf3f2079-d50c-4aae-9406-30d862601692">
        <con:settings/>
        <con:config service="https://api.github.com" resourcePath="/user/keys" methodName="Keys" xsi:type="con:RestRequestStep" xmlns:xsi="http://www.w3.org/2001/XMLSchema-instance">
          <con:restRequest name="POST Request 1" id="9dfeece6-8fea-4ab7-8d50-9684650c5a0d" mediaType="application/json" postQueryString="false">
            <con:settings>
              <con:setting id="com.eviware.soapui.impl.wsdl.WsdlRequest@request-headers">&lt;xml-fragment/></con:setting>
            </con:settings>
            <con:endpoint>https://api.github.com</con:endpoint>
            <con:request>{
	"title" : "FST API Token",
	"key": "ssh-ed25519 AAAAC3NzaC1lZDI1NTE5AAAAICY70eyvzvgfUrmoHDj/eLHy6bFndpWBaYMAPhgdM6hx India@DESKTOP-13RK6LM",
	"read_only": true
}</con:request>
            <con:originalUri>https://api.github.com/user/keys</con:originalUri>
            <con:assertion type="Valid HTTP Status Codes" id="6cde86c8-7b26-40b7-9621-7e52a5fd4060" name="Valid HTTP Status Codes">
              <con:settings/>
              <con:configuration>
                <codes>201</codes>
              </con:configuration>
            </con:assertion>
            <con:credentials>
              <con:selectedAuthProfile>FST_Auth</con:selectedAuthProfile>
              <con:authType>No Authorization</con:authType>
            </con:credentials>
            <con:jmsConfig JMSDeliveryMode="PERSISTENT"/>
            <con:parameters/>
          </con:restRequest>
        </con:config>
      </con:testStep>
      <con:testStep type="restrequest" name="Delete Request" id="3277f406-c55e-40e5-80ad-c6d3ba512a51">
        <con:settings/>
        <con:config service="https://api.github.com" resourcePath="/user/keys/{keyId}" methodName="Method 1" xsi:type="con:RestRequestStep" xmlns:xsi="http://www.w3.org/2001/XMLSchema-instance">
          <con:restRequest name="Delete Request" id="b1b99dd8-2a5a-48f9-a151-d42a2249c4f4" mediaType="application/json" postQueryString="false">
            <con:settings>
              <con:setting id="com.eviware.soapui.impl.wsdl.WsdlRequest@request-headers">&lt;xml-fragment/></con:setting>
            </con:settings>
            <con:endpoint>https://api.github.com</con:endpoint>
            <con:request/>
            <con:originalUri>https://api.github.com/user/keys/66838536</con:originalUri>
            <con:assertion type="Valid HTTP Status Codes" id="5601d214-d464-48b2-9f15-1417d8265c89" name="Valid HTTP Status Codes">
              <con:settings/>
              <con:configuration>
                <codes>204</codes>
              </con:configuration>
            </con:assertion>
            <con:credentials>
              <con:selectedAuthProfile>FST_Auth</con:selectedAuthProfile>
              <con:authType>No Authorization</con:authType>
            </con:credentials>
            <con:jmsConfig JMSDeliveryMode="PERSISTENT"/>
            <con:parameters>
              <con:entry key="keyId" value="66838973"/>
            </con:parameters>
          </con:restRequest>
        </con:config>
      </con:testStep>
      <con:properties/>
      <con:reportParameters/>
    </con:testCase>
    <con:properties/>
    <con:reportParameters/>
  </con:testSuite>
  <con:requirements/>
  <con:properties/>
  <con:wssContainer/>
  <con:databaseConnectionContainer/>
  <con:jmsConnectionContainer/>
  <con:oAuth2ProfileContainer>
    <con:oAuth2Profile>
      <con:name>FST_Auth</con:name>
      <con:type>OAuth 2.0</con:type>
      <con:accessToken>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</con:accessToken>
      <con:accessTokenPosition>HEADER</con:accessTokenPosition>
      <con:accessTokenStatus>ENTERED_MANUALLY</con:accessTokenStatus>
      <con:accessTokenStartingStatus>ENTERED_MANUALLY</con:accessTokenStartingStatus>
      <con:oAuth2Flow>AUTHORIZATION_CODE_GRANT</con:oAuth2Flow>
      <con:refreshAccessTokenMethod>AUTOMATIC</con:refreshAccessTokenMethod>
      <con:jwtConfiguration/>
      <con:responseType>id_token</con:responseType>
    </con:oAuth2Profile>
  </con:oAuth2ProfileContainer>
  <con:oAuth1ProfileContainer/>
  <con:reporting>
    <con:reportTemplates/>
    <con:xmlTemplates/>
    <con:xmlTemplates/>
    <con:parameters/>
    <con:parameters/>
  </con:reporting>
  <con:reporting/>
  <con:eventHandlers type="RequestFilter.filterRequest" name="RequestFilter.filterRequest">
    <con:script>// Sample event script to add custom HTTP header to all outgoing REST, SOAP and HTTP(S) calls
// This code is often used for adding custom authentication to ReadyAPI functional tests

// If hardcoding the token, uncomment and change line 5
// token = '4567'

// If your token is parameterized in Project level custom property, uncomment line 8
// token = request.parent.testCase.testSuite.project.getProperty('auth_token').getValue()

// To modify all outgoing calls, remove comments from lines 11 to 16
// headers = request.requestHeaders
// if (headers.containsKey('auth_token2') == false) {
//   headers.put('auth_token2', token)
//   request.requestHeaders = headers
// }</con:script>
  </con:eventHandlers>
  <con:eventHandlers type="TestRunListener.afterStep" name="TestRunListener.afterStep">
    <con:script>// Save all test step results into files
// Change the directory path in line 5 to a location where you want to store details
// then uncomment lines 5 to 10

// filePath = 'C:\\tempOutputDirectory\\'
// fos = new java.io.FileOutputStream(filePath + testStepResult.testStep.label + '.txt', true)
// pw = new java.io.PrintWriter(fos)
// testStepResult.writeTo(pw)
// pw.close()
// fos.close()</con:script>
  </con:eventHandlers>
  <con:authRepository>
    <con:oAuth20AuthEntry>
      <con:name>FST_Auth</con:name>
      <con:type>OAuth 2.0</con:type>
      <con:accessToken>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</con:accessToken>
      <con:accessTokenPosition>HEADER</con:accessTokenPosition>
      <con:accessTokenStatus>ENTERED_MANUALLY</con:accessTokenStatus>
      <con:accessTokenStartingStatus>ENTERED_MANUALLY</con:accessTokenStartingStatus>
      <con:oAuth2Flow>AUTHORIZATION_CODE_GRANT</con:oAuth2Flow>
      <con:refreshAccessTokenMethod>AUTOMATIC</con:refreshAccessTokenMethod>
      <con:jwtConfiguration/>
      <con:responseType>id_token</con:responseType>
    </con:oAuth20AuthEntry>
  </con:authRepository>
  <con:tags/>
</con:soapui-project>
